CHANGELOG.txt
LICENCE.txt
MANIFEST.in
README.md
commands.txt
run.py
setup.py
nativeUts/__init__.py
nativeUts/dict.py
nativeUts/list.py
nativeUts/number.py
nativeUts/pandas.py
nativeUts/path.py
nativeUts/string.py
nativeUts.egg-info/PKG-INFO
nativeUts.egg-info/SOURCES.txt
nativeUts.egg-info/dependency_links.txt
nativeUts.egg-info/requires.txt
nativeUts.egg-info/top_level.txt