Metadata-Version: 2.1
Name: nativeUts
Version: 1.0.2
Summary: A Python package for native utilities.
Home-page: 
Author: Melque Lima
Author-email: melque_ex@yahoo.com.br
License: MIT
Keywords: nativeUts
Classifier: Development Status :: 5 - Production/Stable
Classifier: Intended Audience :: Education
Classifier: Operating System :: Microsoft :: Windows :: Windows 10
Classifier: License :: OSI Approved :: MIT License
Classifier: Programming Language :: Python :: 3
License-File: LICENCE.txt
Requires-Dist: forbiddenfruit==0.1.4
